sortByTanvir
