Metadata-Version: 2.1
Name: sortByTanvir
Version: 1.0.3
Summary: A simple sorting algorithms education package
Home-page: https://github.com/Tanvir-yzu/sortByTanvir.git
Author: Tanvir-yzu
Author-email: 2020tanvir1971@gmail.com
Classifier: Development Status :: 3 - Alpha
Classifier: Intended Audience :: Education
Classifier: License :: OSI Approved :: MIT License
Classifier: Programming Language :: Python :: 3.6
License-File: LICENCE.txt
